mxnet_cu102mkl-1.6.0.post0.dist-info/metadata.json
mxnet_cu102mkl-1.6.0.post0.dist-info/METADATA
mxnet_cu102mkl-1.6.0.post0.dist-info/WHEEL
mxnet_cu102mkl-1.6.0.post0.dist-info/DESCRIPTION.rst
mxnet_cu102mkl-1.6.0.post0.dist-info/RECORD
mxnet_cu102mkl-1.6.0.post0.dist-info/top_level.txt
mxnet/callback.py
mxnet/rtc.py
mxnet/log.py
mxnet/libmkldnn.so.1
mxnet/kvstore.py
mxnet/profiler.py
mxnet/space.py
mxnet/libquadmath.so.0
mxnet/COMMIT_HASH
mxnet/model.py
mxnet/libiomp5.so
mxnet/numpy_op_signature.py
mxnet/runtime.py
mxnet/util.py
mxnet/random.py
mxnet/MKLML_LICENSE
mxnet/autograd.py
mxnet/executor.py
mxnet/symbol_doc.py
mxnet/registry.py
mxnet/_numpy_op_doc.py
mxnet/ndarray_doc.py
mxnet/metric.py
mxnet/test_utils.py
mxnet/visualization.py
mxnet/torch.py
mxnet/numpy_dispatch_protocol.py
mxnet/executor_manager.py
mxnet/__init__.py
mxnet/attribute.py
mxnet/libmkldnn.so.0
mxnet/context.py
mxnet/libmklml_intel.so
mxnet/CUB_LICENSE
mxnet/tvmop.py
mxnet/engine.py
mxnet/libinfo.py
mxnet/numpy_op_fallback.py
mxnet/lr_scheduler.py
mxnet/libgfortran.so.3
mxnet/recordio.py
mxnet/monitor.py
mxnet/misc.py
mxnet/base.py
mxnet/operator.py
mxnet/library.py
mxnet/initializer.py
mxnet/libmxnet.so
mxnet/name.py
mxnet/kvstore_server.py
mxnet/symbol/gen_image.py
mxnet/symbol/linalg.py
mxnet/symbol/sparse.py
mxnet/symbol/gen_random.py
mxnet/symbol/gen_sparse.py
mxnet/symbol/_internal.py
mxnet/symbol/random.py
mxnet/symbol/contrib.py
mxnet/symbol/gen_linalg.py
mxnet/symbol/__init__.py
mxnet/symbol/gen_op.py
mxnet/symbol/gen_contrib.py
mxnet/symbol/symbol.py
mxnet/symbol/gen__internal.py
mxnet/symbol/image.py
mxnet/symbol/op.py
mxnet/symbol/register.py
mxnet/symbol/numpy_extension/random.py
mxnet/symbol/numpy_extension/_op.py
mxnet/symbol/numpy_extension/__init__.py
mxnet/symbol/numpy_extension/_register.py
mxnet/symbol/numpy_extension/image.py
mxnet/symbol/numpy/linalg.py
mxnet/symbol/numpy/_internal.py
mxnet/symbol/numpy/random.py
mxnet/symbol/numpy/_op.py
mxnet/symbol/numpy/__init__.py
mxnet/symbol/numpy/_register.py
mxnet/symbol/numpy/_symbol.py
mxnet/numpy_extension/random.py
mxnet/numpy_extension/_op.py
mxnet/numpy_extension/__init__.py
mxnet/numpy_extension/utils.py
